setup.py
gnulynx/__init__.py
gnulynx/cli.py
gnulynx/cli_util.py
gnulynx/exceptions.py
gnulynx/serialize.py
gnulynx/settings.py
gnulynx/task.py
gnulynx/util.py
gnulynx.egg-info/PKG-INFO
gnulynx.egg-info/SOURCES.txt
gnulynx.egg-info/dependency_links.txt
gnulynx.egg-info/eager_resources.txt
gnulynx.egg-info/entry_points.txt
gnulynx.egg-info/namespace_packages.txt
gnulynx.egg-info/not-zip-safe
gnulynx.egg-info/top_level.txt
gnulynx/tasks/__init__.py
gnulynx/tasks/articles/__init__.py
gnulynx/tasks/articles/feed.py
gnulynx/tasks/articles/homepage.py
gnulynx/tasks/facebook/__init__.py
gnulynx/tasks/facebook/insights.py
gnulynx/tasks/facebook/page.py
gnulynx/tasks/facebook/page_stats.py
gnulynx/tasks/facebook/shares.py
gnulynx/tasks/google_alerts/__init__.py
gnulynx/tasks/google_alerts/feed.py
gnulynx/tasks/google_analytics/__init__.py
gnulynx/tasks/hacker_news/__init__.py
gnulynx/tasks/hacker_news/comments.py
gnulynx/tasks/hacker_news/posts.py
gnulynx/tasks/hacker_news/util.py
gnulynx/tasks/homepage/__init__.py
gnulynx/tasks/homepage/articles.py
gnulynx/tasks/homepage/stats.py
gnulynx/tasks/linkedin/__init__.py
gnulynx/tasks/linkedin/shares.py
gnulynx/tasks/pinterest/__init__.py
gnulynx/tasks/pinterest/shares.py
gnulynx/tasks/reddit/__init__.py
gnulynx/tasks/reddit/search.py
gnulynx/tasks/reddit/shares.py
gnulynx/tasks/scrape/__init__.py
gnulynx/tasks/scrape/muckrack.py
gnulynx/tasks/sql/__init__.py
gnulynx/tasks/sql/bulk_insert.py
gnulynx/tasks/sql/insert.py
gnulynx/tasks/sql/query.py
gnulynx/tasks/sql/upsert.py
gnulynx/tasks/sql/util.py
gnulynx/tasks/to/__init__.py
gnulynx/tasks/to/json.py
gnulynx/tasks/to/json_gz.py
gnulynx/tasks/to/yml.py
gnulynx/tasks/to/yml_gz.py
gnulynx/tasks/twitter/__init__.py
gnulynx/tasks/twitter/list.py
gnulynx/tasks/twitter/search.py
gnulynx/tasks/twitter/shares.py
gnulynx/tasks/twitter/stream.py
gnulynx/tasks/twitter/user.py
gnulynx/tasks/twitter/user_stats.py