Metadata-Version: 1.1
Name: gnulynx
Version: 0.1.2
Summary: a task-based command line interface for analytics data
Home-page: http://github.com/newslynx/gnulynx
Author: Brian Abelson
Author-email: brian@newslynx.org
License: MIT
Platform: UNKNOWN
Classifier: Development Status :: 3 - Alpha
Classifier: Intended Audience :: Developers
Classifier: License :: OSI Approved :: MIT License
Classifier: Operating System :: OS Independent
Classifier: Programming Language :: Python
